schoolware_api/__init__.py
schoolware_api/schoolware_api.py
schoolware_api/tests.py
schoolware_api-1.13.5.dist-info/METADATA
schoolware_api-1.13.5.dist-info/WHEEL
schoolware_api-1.13.5.dist-info/top_level.txt
schoolware_api-1.13.5.dist-info/RECORD
