Metadata-Version: 2.1
Name: schoolware_api
Version: 1.13.5
Summary: A api for schoolware written in python
Author: Maarten Buelens
Author-email: MB <schoolware_api@mb-server.com>
Project-URL: Homepage, https://github.com/Maarten-buelens/schoolware_api
Project-URL: Bug Tracker, https://github.com/Maarten-buelens/schoolware_api/issues
Classifier: Programming Language :: Python :: 3
Classifier: License :: OSI Approved :: MIT License
Classifier: Operating System :: OS Independent
Requires-Python: >=3.7
Requires-Dist: requests >=2.25.1
Requires-Dist: playwright >=1.31.1
